fipper
