Metadata-Version: 2.1
Name: fipper
Version: 0.1.3
Summary: Fipper - Telegram MTProto API Client Library for Python.
Home-page: https://github.com/AyiinXd/fipper
Author: AyiinXd
Author-email: ayingaming98@gmail.com
License: GNU Lesser General Public License v3.0 (LGPL-3.0)
Project-URL: Bug Tracker, https://github.com/AyiinXd/fipper/issues
Project-URL: Documentation, https://fipper.tech
Project-URL: Source Code, https://github.com/AyiinXd/fipper
Classifier: Programming Language :: Python :: 3
Classifier: Programming Language :: Python :: 3.8
Classifier: Programming Language :: Python :: 3.9
Classifier: Programming Language :: Python :: 3.10
Classifier: License :: OSI Approved :: GNU General Public License v3 (GPLv3)
Classifier: Operating System :: OS Independent
Requires-Python: ~=3.7
License-File: LICENSE
License-File: NOTICE
Requires-Dist: screeninfo
Requires-Dist: pyaes ==1.6.1
Requires-Dist: pysocks ==1.7.1
Requires-Dist: pyyaml ==6.0.1
Requires-Dist: motor ==3.2.0
Requires-Dist: pymongo ==4.4.1
Requires-Dist: aiosqlite <0.18.0,>=0.16.0
Requires-Dist: aiohttp ==3.8.5
